README.rst
setup.py
infi/__init__.py
infi.unittest.egg-info/PKG-INFO
infi.unittest.egg-info/SOURCES.txt
infi.unittest.egg-info/dependency_links.txt
infi.unittest.egg-info/entry_points.txt
infi.unittest.egg-info/namespace_packages.txt
infi.unittest.egg-info/requires.txt
infi.unittest.egg-info/top_level.txt
infi/unittest/__init__.py
infi/unittest/__version__.py
infi/unittest/_compat.py
infi/unittest/abstract_base.py
infi/unittest/call.py
infi/unittest/case.py
infi/unittest/exceptions.py
infi/unittest/filter_syntax.py
infi/unittest/loader.py
infi/unittest/nose_plugin.py
infi/unittest/parameters.py
infi/unittest/result.py
infi/unittest/test_filter.py