Metadata-Version: 1.1
Name: infi.unittest
Version: 1.0.0
Summary: Unittest extension library
Home-page: UNKNOWN
Author: Rotem Yaari
Author-email: UNKNOWN
License: BSD
Platform: UNKNOWN
Classifier: Development Status :: 4 - Beta
Classifier: Intended Audience :: Developers
Classifier: Programming Language :: Python :: 2.7
